{"data": [{"zrxh": 7, "jybz": "0", "jyrq": "2018-12-01"}, {"zrxh": 1, "jybz": "0", "jyrq": "2018-12-02"}, {"zrxh": 2, "jybz": "1", "jyrq": "2018-12-03"}, {"zrxh": 3, "jybz": "1", "jyrq": "2018-12-04"}, {"zrxh": 4, "jybz": "1", "jyrq": "2018-12-05"}, {"zrxh": 5, "jybz": "1", "jyrq": "2018-12-06"}, {"zrxh": 6, "jybz": "1", "jyrq": "2018-12-07"}, {"zrxh": 7, "jybz": "0", "jyrq": "2018-12-08"}, {"zrxh": 1, "jybz": "0", "jyrq": "2018-12-09"}, {"zrxh": 2, "jybz": "1", "jyrq": "2018-12-10"}, {"zrxh": 3, "jybz": "1", "jyrq": "2018-12-11"}, {"zrxh": 4, "jybz": "1", "jyrq": "2018-12-12"}, {"zrxh": 5, "jybz": "1", "jyrq": "2018-12-13"}, {"zrxh": 6, "jybz": "1", "jyrq": "2018-12-14"}, {"zrxh": 7, "jybz": "0", "jyrq": "2018-12-15"}, {"zrxh": 1, "jybz": "0", "jyrq": "2018-12-16"}, {"zrxh": 2, "jybz": "1", "jyrq": "2018-12-17"}, {"zrxh": 3, "jybz": "1", "jyrq": "2018-12-18"}, {"zrxh": 4, "jybz": "1", "jyrq": "2018-12-19"}, {"zrxh": 5, "jybz": "1", "jyrq": "2018-12-20"}, {"zrxh": 6, "jybz": "1", "jyrq": "2018-12-21"}, {"zrxh": 7, "jybz": "0", "jyrq": "2018-12-22"}, {"zrxh": 1, "jybz": "0", "jyrq": "2018-12-23"}, {"zrxh": 2, "jybz": "1", "jyrq": "2018-12-24"}, {"zrxh": 3, "jybz": "1", "jyrq": "2018-12-25"}, {"zrxh": 4, "jybz": "1", "jyrq": "2018-12-26"}, {"zrxh": 5, "jybz": "1", "jyrq": "2018-12-27"}, {"zrxh": 6, "jybz": "1", "jyrq": "2018-12-28"}, {"zrxh": 7, "jybz": "0", "jyrq": "2018-12-29"}, {"zrxh": 1, "jybz": "0", "jyrq": "2018-12-30"}, {"zrxh": 2, "jybz": "0", "jyrq": "2018-12-31"}], "nowdate": "2025-06-19"}